{"type": "7z", "size": 24468, "method": "LZMA:192k", "solid": true, "files": [{"name": "01 Title.vgm", "size": 16316, "crc": "5B898449"}, {"name": "02 Credit.vgm", "size": 3093, "crc": "D258697A"}, {"name": "03 Main BGM.vgm", "size": 2361, "crc": "88460007"}, {"name": "04 Slot Stage.vgm", "size": 16258, "crc": "7920232C"}, {"name": "05 Card Stage.vgm", "size": 12479, "crc": "6D5AAB35"}, {"name": "06 Bowling Stage.vgm", "size": 9427, "crc": "42B8F458"}, {"name": "07 Game Over.vgm", "size": 2013, "crc": "4B2963A4"}, {"name": "08 Name Entry (1st Place).vgm", "size": 33923, "crc": "924C84FE"}, {"name": "09 Name Entry (Below 2nd Place).vgm", "size": 36084, "crc": "57DBB872"}, {"name": "Pinball Action.png", "size": 1685, "crc": "DE2E3D33"}, {"name": "Pinball Action.txt", "size": 1469, "crc": "A8BC307D"}]}