{"type": "7z", "size": 70536223, "method": "Copy", "solid": false, "files": [{"name": "Ariella_Stealthy_Skirmish.fsb", "size": 1456752, "time": "2018-10-27 17:49:52", "crc": "8476644C"}, {"name": "Boss_2_Stem_Percussion.fsb", "size": 1744552, "time": "2018-10-27 17:45:24", "crc": "02EE85B1"}, {"name": "Champions of Canaan Theme_Opt_2.fsb", "size": 5631000, "time": "2018-10-27 17:45:24", "crc": "7C17BA2E"}, {"name": "five_cave_interior.fsb", "size": 1224760, "time": "2018-10-27 17:58:41", "crc": "1F933511"}, {"name": "FIVE_MainTheme.fsb", "size": 7030152, "time": "2018-10-27 17:58:15", "crc": "7837109E"}, {"name": "IntroMovie.fsb", "size": 2628448, "time": "2018-10-27 17:58:15", "crc": "A74F6022"}, {"name": "IntroMovie2.fsb", "size": 540752, "time": "2018-10-27 17:58:15", "crc": "B0274238"}, {"name": "mission_advance.fsb", "size": 109968, "time": "2018-10-27 17:48:34", "crc": "7C31DEAD"}, {"name": "music_A1L3_Intro.fsb", "size": 3898464, "time": "2018-10-27 17:39:05", "crc": "7B0EA194"}, {"name": "music_amak_dialog.fsb", "size": 1211856, "time": "2018-10-27 17:47:19", "crc": "E2B118E6"}, {"name": "music_ammonite_cine.fsb", "size": 1869512, "time": "2018-10-27 17:44:55", "crc": "18A7824F"}, {"name": "music_ammonite_combat.fsb", "size": 2359856, "time": "2018-10-27 17:44:55", "crc": "09F68569"}, {"name": "music_ammonite_dialog.fsb", "size": 1383248, "time": "2018-10-27 17:47:19", "crc": "4A6302B9"}, {"name": "Music_Boss_1.fsb", "size": 1374848, "time": "2018-10-27 18:10:23", "crc": "2999E652"}, {"name": "Music_Boss_2.fsb", "size": 1517160, "time": "2018-10-27 18:11:05", "crc": "525704C1"}, {"name": "Music_Boss_3.fsb", "size": 1619184, "time": "2018-10-27 18:09:45", "crc": "D98C8F57"}, {"name": "music_edomite_combat.fsb", "size": 1837608, "time": "2018-10-27 18:01:26", "crc": "D3DC8876"}, {"name": "music_edomite_cutscene.fsb", "size": 1896768, "time": "2018-10-27 18:01:26", "crc": "16C8D9DD"}, {"name": "music_edomite_dialog.fsb", "size": 1640080, "time": "2018-10-27 18:01:26", "crc": "8CE9843B"}, {"name": "music_israelite_cave.fsb", "size": 5024832, "time": "2018-10-27 18:01:46", "crc": "9CD57481"}, {"name": "music_israelite_cinematic_phil.fsb", "size": 1134848, "time": "2018-10-27 17:56:04", "crc": "2A24931B"}, {"name": "music_israelite_combat_end.fsb", "size": 125176, "time": "2018-10-27 17:56:04", "crc": "9922C73F"}, {"name": "music_israelite_combat_loop.fsb", "size": 2417880, "time": "2018-10-27 17:56:04", "crc": "E71114A1"}, {"name": "music_israelite_dialog_bed_2.fsb", "size": 851680, "time": "2018-10-27 17:56:04", "crc": "5177C122"}, {"name": "music_israelite_dialog_bed_3.fsb", "size": 835312, "time": "2018-10-27 17:56:04", "crc": "5420C2B7"}, {"name": "music_israelite_dialog_bed_30.fsb", "size": 845856, "time": "2018-10-27 17:56:04", "crc": "7151B7A1"}, {"name": "music_israelite_discovery.fsb", "size": 172904, "time": "2018-10-27 17:48:34", "crc": "C7E1724A"}, {"name": "music_israelite_intro.fsb", "size": 1040944, "time": "2018-10-27 17:39:28", "crc": "A555D156"}, {"name": "music_moabite_cine.fsb", "size": 1567128, "time": "2018-10-27 17:48:57", "crc": "7396F157"}, {"name": "music_moabite_combat.fsb", "size": 882032, "time": "2018-10-27 17:48:57", "crc": "12CD5A88"}, {"name": "music_moabite_dialog.fsb", "size": 1642712, "time": "2018-10-27 17:48:57", "crc": "70F117AE"}, {"name": "music_philistine_cinematic.fsb", "size": 1283912, "time": "2018-10-27 18:08:17", "crc": "9764B8D8"}, {"name": "music_philistine_combat.fsb", "size": 2282244, "time": "2018-10-27 17:56:09", "crc": "829E3675"}, {"name": "music_philistine_dialog.fsb", "size": 1961408, "time": "2018-10-27 17:56:09", "crc": "6A018A55"}, {"name": "Music_Skirmish_1.fsb", "size": 1378512, "time": "2018-10-27 18:07:14", "crc": "E3F6BF9F"}, {"name": "Music_Skirmish_2.fsb", "size": 1516528, "time": "2018-10-27 18:09:45", "crc": "50E02C4A"}, {"name": "Music_Skirmish_3.fsb", "size": 1371312, "time": "2018-10-27 18:11:05", "crc": "9DC65F81"}, {"name": "Music_Skirmish_4.fsb", "size": 1624312, "time": "2018-10-27 18:10:23", "crc": "89FEE39C"}, {"name": "Player_Level_Up_01.fsb", "size": 142872, "time": "2018-10-27 17:49:26", "crc": "DC109868"}, {"name": "resurrect_sting.fsb", "size": 166920, "time": "2018-10-27 17:48:34", "crc": "1216ACBB"}, {"name": "Skirmish_3_Stem_Strings.fsb", "size": 1290872, "time": "2018-10-27 17:45:24", "crc": "72E0D50F"}]}