{"type": "7z", "size": 98738612, "method": "LZMA2:6m", "solid": false, "files": [{"name": "00.ogg", "size": 4686796, "time": "2021-08-09 04:19:16", "crc": "E9F0C124"}, {"name": "01.ogg", "size": 2993531, "time": "2021-08-09 04:19:17", "crc": "918BB379"}, {"name": "02.ogg", "size": 2786298, "time": "2021-08-09 04:19:17", "crc": "49E84CCE"}, {"name": "03.ogg", "size": 3584200, "time": "2021-08-09 04:19:17", "crc": "615BF50F"}, {"name": "04.ogg", "size": 3173353, "time": "2021-08-09 04:19:17", "crc": "4A1BC097"}, {"name": "05.ogg", "size": 3876989, "time": "2021-08-09 04:19:17", "crc": "224418EC"}, {"name": "06.ogg", "size": 3159442, "time": "2021-08-09 04:19:17", "crc": "EE89207D"}, {"name": "07.ogg", "size": 2491047, "time": "2021-08-09 04:19:17", "crc": "C1B61CD2"}, {"name": "08.ogg", "size": 3464511, "time": "2021-08-09 04:19:17", "crc": "2AC2FA31"}, {"name": "09.ogg", "size": 3008342, "time": "2021-08-09 04:19:17", "crc": "28F8FAEF"}, {"name": "10.ogg", "size": 3509143, "time": "2021-08-09 04:19:17", "crc": "98B07A0F"}, {"name": "11.ogg", "size": 1955790, "time": "2021-08-09 04:19:17", "crc": "18083BF4"}, {"name": "12.ogg", "size": 6126379, "time": "2021-08-09 04:19:17", "crc": "96C0C5B3"}, {"name": "20.ogg", "size": 1623819, "time": "2021-08-09 04:19:17", "crc": "62072263"}, {"name": "21.ogg", "size": 1771005, "time": "2021-08-09 04:19:17", "crc": "C10F3DE4"}, {"name": "22.ogg", "size": 2261301, "time": "2021-08-09 04:19:17", "crc": "D7D30F51"}, {"name": "23.ogg", "size": 1938256, "time": "2021-08-09 04:19:17", "crc": "3B2FEFB8"}, {"name": "24.ogg", "size": 1897084, "time": "2021-08-09 04:19:17", "crc": "E6039FA0"}, {"name": "25.ogg", "size": 1068266, "time": "2021-08-09 04:19:17", "crc": "243B8888"}, {"name": "26.ogg", "size": 2285850, "time": "2021-08-09 04:19:17", "crc": "4E863937"}, {"name": "27.ogg", "size": 1544460, "time": "2021-08-09 04:19:17", "crc": "376C0E70"}, {"name": "28.ogg", "size": 2059295, "time": "2021-08-09 04:19:17", "crc": "53A70824"}, {"name": "29.ogg", "size": 2361736, "time": "2021-08-09 04:19:17", "crc": "6CC60806"}, {"name": "31.ogg", "size": 1735150, "time": "2021-08-09 04:19:17", "crc": "75A784A8"}, {"name": "32.ogg", "size": 3399754, "time": "2021-08-09 04:19:18", "crc": "BFAF5590"}, {"name": "33.ogg", "size": 1868111, "time": "2021-08-09 04:19:18", "crc": "8AB501D1"}, {"name": "34.ogg", "size": 2275031, "time": "2021-08-09 04:19:18", "crc": "C568F42B"}, {"name": "35.ogg", "size": 2917382, "time": "2021-08-09 04:19:18", "crc": "1D5DA5F5"}, {"name": "36.ogg", "size": 2042083, "time": "2021-08-09 04:19:18", "crc": "59027AA6"}, {"name": "37.ogg", "size": 2709894, "time": "2021-08-09 04:19:18", "crc": "C237424C"}, {"name": "38.ogg", "size": 2260999, "time": "2021-08-09 04:19:18", "crc": "41EFE135"}, {"name": "39.ogg", "size": 4629156, "time": "2021-08-09 04:19:18", "crc": "BF4AB6F5"}, {"name": "40.ogg", "size": 2207958, "time": "2021-08-09 04:19:18", "crc": "0FFB6EC1"}, {"name": "41.ogg", "size": 1978664, "time": "2021-08-09 04:19:18", "crc": "C49FF3B2"}, {"name": "42.ogg", "size": 1648793, "time": "2021-08-09 04:19:18", "crc": "1346A738"}, {"name": "43.ogg", "size": 2579199, "time": "2021-08-09 04:19:18", "crc": "5EB6472A"}, {"name": "44.ogg", "size": 2050592, "time": "2021-08-09 04:19:18", "crc": "6FF68779"}, {"name": "ed.ogg", "size": 1785917, "time": "2021-08-09 04:19:18", "crc": "3FEB0A20"}, {"name": "info.txt", "size": 21, "time": "2020-05-16 11:47:04", "crc": "1F3E0BAE"}]}