{"type": "7z", "size": 51037139, "method": "LZMA2:24", "solid": true, "files": [{"name": "ApproachingElevator.ogg", "size": 1690885, "time": "2020-06-17 22:36:26", "crc": "209ED4DC"}, {"name": "ApproachingMayor.ogg", "size": 1602922, "time": "2020-06-17 22:36:26", "crc": "9137DE0E"}, {"name": "AscendingElevatorandtop.ogg", "size": 3173643, "time": "2020-06-17 22:36:26", "crc": "F9308DD0"}, {"name": "BlueAgeEntrance_01.ogg", "size": 1580994, "time": "2020-06-17 22:36:26", "crc": "7AA31F2A"}, {"name": "Credits.ogg", "size": 2303699, "time": "2020-06-17 22:36:26", "crc": "7C9FD89B"}, {"name": "Cyan_Logo.mp4.aac", "size": 447094, "time": "2020-06-18 13:55:17", "crc": "912FA645"}, {"name": "DanceOfTheRussianSubmarine.ogg", "size": 1821940, "time": "2020-06-17 22:36:26", "crc": "B36D53C4"}, {"name": "Diaspora.ogg", "size": 2189040, "time": "2020-06-17 22:36:26", "crc": "D0B826AA"}, {"name": "Earth.ogg", "size": 2314916, "time": "2020-06-17 22:36:26", "crc": "A030D8AB"}, {"name": "End_Game_D.ogg", "size": 1800438, "time": "2020-06-17 22:36:25", "crc": "B40E84A8"}, {"name": "EndGameE.ogg", "size": 1614369, "time": "2020-06-17 22:36:25", "crc": "37A2FA31"}, {"name": "FarleyThemeSong_1.ogg", "size": 1066588, "time": "2020-06-17 22:36:26", "crc": "B15F5B0B"}, {"name": "Generator_w-Changes.ogg", "size": 2123101, "time": "2020-06-17 22:36:26", "crc": "58D47320"}, {"name": "HiveSecondTry_1.ogg", "size": 1473892, "time": "2020-06-17 22:36:26", "crc": "58B950D4"}, {"name": "Hub_Empty.ogg", "size": 2264082, "time": "2020-06-17 22:36:26", "crc": "8EB3B17A"}, {"name": "Hub_Water_vs_B_01.ogg", "size": 1911298, "time": "2020-06-17 22:36:26", "crc": "DBE8BAAE"}, {"name": "Hunrath_AreaB.ogg", "size": 1009018, "time": "2020-06-17 22:36:26", "crc": "D2FA7EBE"}, {"name": "Hunrath_CWFirstVisit.ogg", "size": 1438068, "time": "2020-06-17 22:36:26", "crc": "2B6ACBC4"}, {"name": "Hunrath_CWShack.ogg", "size": 1550359, "time": "2020-06-17 22:36:26", "crc": "464B5D93"}, {"name": "Hunrath_Entrance_2ndVers.ogg", "size": 1662833, "time": "2020-06-17 22:36:26", "crc": "3C940F45"}, {"name": "Hunrath_FarleyMusicBox.ogg", "size": 397592, "time": "2020-06-17 22:36:26", "crc": "61D7051C"}, {"name": "Hunrath_MayorRecordPlayer.ogg", "size": 432232, "time": "2020-06-17 22:36:26", "crc": "53984C5F"}, {"name": "Intro_-_Attempt3_01_proto.ogg", "size": 2035053, "time": "2020-06-17 22:36:26", "crc": "640E83B5"}, {"name": "intro_forest.ogg", "size": 1680939, "time": "2020-06-17 22:36:26", "crc": "D44C4B49"}, {"name": "Intro_Seed.ogg", "size": 638044, "time": "2020-06-17 22:36:26", "crc": "878304E5"}, {"name": "Kaptar_UpHigh.ogg", "size": 1726977, "time": "2020-06-17 22:36:26", "crc": "EA81CEB1"}, {"name": "Kaptor_EndofHive.ogg", "size": 2026760, "time": "2020-06-17 22:36:26", "crc": "93B74A01"}, {"name": "Mayor_INT.ogg", "size": 1238388, "time": "2020-06-17 22:36:26", "crc": "270FC557"}, {"name": "Moria_05.ogg", "size": 2204682, "time": "2020-06-17 22:36:26", "crc": "3A89821B"}, {"name": "SoriaDeathMarch.ogg", "size": 2083089, "time": "2020-06-17 22:36:26", "crc": "DAFC2659"}, {"name": "Swamp_approaching_tree.ogg", "size": 957628, "time": "2020-06-17 22:36:26", "crc": "A47E4912"}, {"name": "Swamp_B27_03.ogg", "size": 1457196, "time": "2020-06-17 22:36:26", "crc": "880AB109"}, {"name": "Swamp_Ride_Post_Ride.ogg", "size": 1335269, "time": "2020-06-17 22:36:26", "crc": "12EC7EE9"}, {"name": "Swamp_WMD.ogg", "size": 1078854, "time": "2020-06-17 22:36:26", "crc": "ECEE8217"}, {"name": "TikiMusic.ogg", "size": 613983, "time": "2020-06-17 22:36:26", "crc": "C5CA0B80"}]}