{"type": "7z", "size": 20050585, "method": "LZMA:24", "solid": true, "files": [{"name": "Amb_St_Windloop.ogg", "size": 101514, "time": "2015-07-12 20:40:06", "crc": "4DB93173"}, {"name": "Boss4_Music.ogg", "size": 5022848, "time": "2015-07-12 20:40:24", "crc": "00048184"}, {"name": "level0_music.ogg", "size": 2149508, "time": "2015-07-12 20:40:28", "crc": "1433569C"}, {"name": "level2_music.ogg", "size": 2138354, "time": "2015-07-12 20:41:04", "crc": "C4626066"}, {"name": "level2b_music.ogg", "size": 1840121, "time": "2015-07-12 20:40:44", "crc": "4630DCED"}, {"name": "level3_music.ogg", "size": 2695519, "time": "2015-07-12 20:41:08", "crc": "37C2EDBB"}, {"name": "level4_music.ogg", "size": 1902379, "time": "2015-07-12 20:40:56", "crc": "98BCF819"}, {"name": "level_victory_music.ogg", "size": 251162, "time": "2015-07-12 20:40:56", "crc": "9F0E652F"}, {"name": "menu_background_music.ogg", "size": 647605, "time": "2015-07-12 20:41:04", "crc": "D9964AFA"}, {"name": "Music_L1_full_1.ogg", "size": 2037948, "time": "2015-07-12 20:41:06", "crc": "37719D79"}, {"name": "SnD_BossMusic_Pitch.ogg", "size": 2332404, "time": "2015-07-12 20:40:58", "crc": "6AF06F15"}]}