{"type": "7z", "size": 406443, "method": "LZMA2:3m", "solid": true, "files": [{"name": "01 Credit ~ Awaiting Entry.vgm", "size": 512731, "time": "2016-06-03 04:37:28", "crc": "22DCCB4C"}, {"name": "02 Entry Closed.vgm", "size": 97479, "time": "2016-06-03 04:37:28", "crc": "64269A1B"}, {"name": "03 Finish A, Name Entry.vgm", "size": 442941, "time": "2016-06-03 04:37:30", "crc": "2F903F5E"}, {"name": "04 Finish B.vgm", "size": 256598, "time": "2016-06-03 04:37:30", "crc": "E69924C5"}, {"name": "05 Finish C.vgm", "size": 367879, "time": "2016-06-03 04:37:30", "crc": "F82CBE58"}, {"name": "06 Finish B (Alternate).vgm", "size": 159731, "time": "2016-06-03 04:37:30", "crc": "C514CAAB"}, {"name": "07 Awaiting Entry.vgm", "size": 445087, "time": "2016-06-03 04:37:30", "crc": "CB1F1D7F"}, {"name": "08 Speaker Test.vgm", "size": 5159, "time": "2016-06-03 04:37:30", "crc": "4FE41212"}, {"name": "09 Unknown 1.vgm", "size": 129076, "time": "2016-06-03 04:37:30", "crc": "148ACAE0"}, {"name": "10 Unknown 2.vgm", "size": 52621, "time": "2016-06-03 04:37:30", "crc": "9587443C"}, {"name": "11 Unknown 3.vgm", "size": 63838, "time": "2016-06-03 04:37:30", "crc": "CA1D2467"}, {"name": "12 Unknown 4.vgm", "size": 114251, "time": "2016-06-03 04:37:30", "crc": "45F6994F"}, {"name": "Four Trax.png", "size": 19687, "time": "2016-04-30 16:09:00", "crc": "292A27FF"}, {"name": "Four Trax.txt", "size": 1488, "time": "2016-05-29 03:53:58", "crc": "7CA12C4A"}]}