{"type": "7z", "size": 10138, "method": "LZMA2:16", "solid": true, "files": [{"name": "01 BGM #01.m3u", "size": 99, "time": "2012-07-31 17:15:40", "crc": "6574A8A0"}, {"name": "02 BGM #02.m3u", "size": 100, "time": "2012-07-31 17:15:40", "crc": "37DD0A2C"}, {"name": "03 BGM #03.m3u", "size": 99, "time": "2012-07-31 17:15:40", "crc": "96D7AC05"}, {"name": "04 BGM #04.m3u", "size": 100, "time": "2012-07-31 17:15:40", "crc": "92B663C4"}, {"name": "05 BGM #05.m3u", "size": 100, "time": "2012-07-31 17:15:40", "crc": "59FF5049"}, {"name": "06 BGM #06.m3u", "size": 100, "time": "2012-07-31 17:15:40", "crc": "A721ABAA"}, {"name": "07 BGM #07.m3u", "size": 100, "time": "2012-07-31 17:15:40", "crc": "D8009EB5"}, {"name": "08 BGM #08.m3u", "size": 99, "time": "2012-07-31 17:15:40", "crc": "01CE17F7"}, {"name": "09 BGM #09.m3u", "size": 100, "time": "2012-07-31 17:15:40", "crc": "6017452D"}, {"name": "10 BGM #10.m3u", "size": 101, "time": "2012-07-31 17:15:40", "crc": "6F038C54"}, {"name": "11 BGM #11.m3u", "size": 100, "time": "2012-07-31 17:15:40", "crc": "290822A5"}, {"name": "12 BGM #12.m3u", "size": 100, "time": "2012-07-31 17:15:40", "crc": "38956DF1"}, {"name": "13 BGM #13.m3u", "size": 101, "time": "2012-07-31 17:15:40", "crc": "F59EE98F"}, {"name": "14 BGM #14.m3u", "size": 100, "time": "2012-07-31 17:15:40", "crc": "A6A10E40"}, {"name": "15 BGM #15.m3u", "size": 100, "time": "2012-07-31 17:15:40", "crc": "972072FA"}, {"name": "16 BGM #16.m3u", "size": 100, "time": "2012-07-31 17:15:40", "crc": "37C92FE9"}, {"name": "17 BGM #17.m3u", "size": 101, "time": "2012-07-31 17:15:40", "crc": "7C7FC45C"}, {"name": "18 Jingle #01.m3u", "size": 102, "time": "2012-07-31 17:15:40", "crc": "EA47378C"}, {"name": "19 Jingle #02.m3u", "size": 102, "time": "2012-07-31 17:15:40", "crc": "725A6B1A"}, {"name": "20 Jingle #03.m3u", "size": 103, "time": "2012-07-31 17:15:40", "crc": "17AD7625"}, {"name": "21 Jingle #04.m3u", "size": 103, "time": "2012-07-31 17:15:40", "crc": "47BD4805"}, {"name": "22 Jingle #05.m3u", "size": 103, "time": "2012-07-31 17:15:40", "crc": "7ADE750E"}, {"name": "23 Jingle #06.m3u", "size": 103, "time": "2012-07-31 17:15:40", "crc": "419060CC"}, {"name": "24 Jingle #07.m3u", "size": 103, "time": "2012-07-31 17:15:40", "crc": "7AD85C78"}, {"name": "25 Jingle #08.m3u", "size": 103, "time": "2012-07-31 17:15:40", "crc": "F63DD9EC"}, {"name": "DMG-AWJJ-JPN.gbs", "size": 15770, "time": "2012-07-24 13:44:47", "crc": "A738CE83"}, {"name": "DMG-AWJJ-JPN.m3u", "size": 1234, "time": "2012-07-31 16:25:40", "crc": "8A0D56D2"}]}