{"type": "7z", "size": 131100, "method": "LZMA2:192k", "solid": true, "files": [{"name": "!playlist.m3u", "size": 1375, "time": "2020-08-17 03:34:40", "crc": "199D6187"}, {"name": "AGB-AY6J-JPN-0000.minigsf", "size": 235, "time": "2021-04-05 06:06:31", "crc": "60BCB5ED"}, {"name": "AGB-AY6J-JPN-0001.minigsf", "size": 240, "time": "2021-04-05 06:06:31", "crc": "FE945AF2"}, {"name": "AGB-AY6J-JPN-0002.minigsf", "size": 240, "time": "2021-04-05 06:06:31", "crc": "91908CCE"}, {"name": "AGB-AY6J-JPN-0003.minigsf", "size": 240, "time": "2021-04-05 06:06:31", "crc": "F70B401A"}, {"name": "AGB-AY6J-JPN-0004.minigsf", "size": 240, "time": "2021-04-05 06:06:31", "crc": "2284144E"}, {"name": "AGB-AY6J-JPN-0005.minigsf", "size": 240, "time": "2021-04-05 06:06:31", "crc": "3D8CDCE5"}, {"name": "AGB-AY6J-JPN-0006.minigsf", "size": 240, "time": "2021-04-05 06:06:31", "crc": "7FE7F0E7"}, {"name": "AGB-AY6J-JPN-0007.minigsf", "size": 240, "time": "2021-04-05 06:06:31", "crc": "BC9D015D"}, {"name": "AGB-AY6J-JPN-0008.minigsf", "size": 239, "time": "2021-04-05 06:06:31", "crc": "36F7D7D1"}, {"name": "AGB-AY6J-JPN-0009.minigsf", "size": 240, "time": "2021-04-05 06:06:31", "crc": "0391574F"}, {"name": "AGB-AY6J-JPN-0010.minigsf", "size": 240, "time": "2021-04-05 06:06:31", "crc": "3D12B1E0"}, {"name": "AGB-AY6J-JPN-0011.minigsf", "size": 240, "time": "2021-04-05 06:06:31", "crc": "19BB6243"}, {"name": "AGB-AY6J-JPN-0012.minigsf", "size": 240, "time": "2021-04-05 06:06:31", "crc": "ED8063A2"}, {"name": "AGB-AY6J-JPN-0013.minigsf", "size": 240, "time": "2021-04-05 06:06:31", "crc": "DA584E6F"}, {"name": "AGB-AY6J-JPN-0014.minigsf", "size": 240, "time": "2021-04-05 06:06:31", "crc": "1CD7E6DD"}, {"name": "AGB-AY6J-JPN-0015.minigsf", "size": 240, "time": "2021-04-05 06:06:31", "crc": "F647D0C3"}, {"name": "AGB-AY6J-JPN-0016.minigsf", "size": 240, "time": "2021-04-05 06:06:31", "crc": "FFA77BBE"}, {"name": "AGB-AY6J-JPN-0017.minigsf", "size": 240, "time": "2021-04-05 06:06:31", "crc": "DECDEB65"}, {"name": "AGB-AY6J-JPN-0018.minigsf", "size": 237, "time": "2021-04-05 06:06:31", "crc": "C7ABAAB6"}, {"name": "AGB-AY6J-JPN-0019.minigsf", "size": 236, "time": "2021-04-05 06:06:31", "crc": "9B46231F"}, {"name": "AGB-AY6J-JPN-0020.minigsf", "size": 240, "time": "2021-04-05 06:06:31", "crc": "07F9C2C9"}, {"name": "AGB-AY6J-JPN-0021.minigsf", "size": 240, "time": "2021-04-05 06:06:31", "crc": "FFB6CA71"}, {"name": "AGB-AY6J-JPN-0022.minigsf", "size": 240, "time": "2021-04-05 06:06:31", "crc": "9CB414FB"}, {"name": "AGB-AY6J-JPN-0023.minigsf", "size": 239, "time": "2021-04-05 06:06:31", "crc": "5A04BB69"}, {"name": "AGB-AY6J-JPN-0024.minigsf", "size": 240, "time": "2021-04-05 06:06:31", "crc": "C422C2A3"}, {"name": "AGB-AY6J-JPN-0025.minigsf", "size": 236, "time": "2021-04-05 06:06:31", "crc": "5A6919CD"}, {"name": "AGB-AY6J-JPN-0026.minigsf", "size": 236, "time": "2021-04-05 06:06:31", "crc": "2348AA6D"}, {"name": "AGB-AY6J-JPN-0027.minigsf", "size": 240, "time": "2021-04-05 06:06:31", "crc": "DD08AB5B"}, {"name": "AGB-AY6J-JPN-0028.minigsf", "size": 238, "time": "2021-04-05 06:06:31", "crc": "5C9514AA"}, {"name": "AGB-AY6J-JPN-0029.minigsf", "size": 238, "time": "2021-04-05 06:06:31", "crc": "18FDEC39"}, {"name": "AGB-AY6J-JPN-0030.minigsf", "size": 240, "time": "2021-04-05 06:06:31", "crc": "E6E2EE4E"}, {"name": "AGB-AY6J-JPN-0031.minigsf", "size": 240, "time": "2021-04-05 06:06:31", "crc": "2D09130F"}, {"name": "AGB-AY6J-JPN-0032.minigsf", "size": 238, "time": "2021-04-05 06:06:31", "crc": "378586CE"}, {"name": "AGB-AY6J-JPN-0033.minigsf", "size": 240, "time": "2021-04-05 06:06:31", "crc": "899F9D73"}, {"name": "AGB-AY6J-JPN-0034.minigsf", "size": 238, "time": "2021-04-05 06:06:31", "crc": "9F6A646F"}, {"name": "AGB-AY6J-JPN-0035.minigsf", "size": 238, "time": "2021-04-05 06:06:31", "crc": "A5A1FCA1"}, {"name": "AGB-AY6J-JPN-0036.minigsf", "size": 238, "time": "2021-04-05 06:06:31", "crc": "5C0DFFF8"}, {"name": "AGB-AY6J-JPN-0037.minigsf", "size": 240, "time": "2021-04-05 06:06:31", "crc": "CD8D793E"}, {"name": "AGB-AY6J-JPN-0038.minigsf", "size": 237, "time": "2021-04-05 06:06:31", "crc": "103B268E"}, {"name": "AGB-AY6J-JPN-0039.minigsf", "size": 240, "time": "2021-04-05 06:06:31", "crc": "39E1D1A5"}, {"name": "AGB-AY6J-JPN-0040.minigsf", "size": 238, "time": "2021-04-05 06:06:31", "crc": "EDFEB452"}, {"name": "AGB-AY6J-JPN-0041.minigsf", "size": 238, "time": "2021-04-05 06:06:31", "crc": "AA1D106A"}, {"name": "AGB-AY6J-JPN-0042.minigsf", "size": 238, "time": "2021-04-05 06:06:31", "crc": "09BF7B54"}, {"name": "AGB-AY6J-JPN-0043.minigsf", "size": 237, "time": "2021-04-05 06:06:31", "crc": "C37D0233"}, {"name": "AGB-AY6J-JPN-0044.minigsf", "size": 240, "time": "2021-04-05 06:06:31", "crc": "01DFF72C"}, {"name": "AGB-AY6J-JPN-0045.minigsf", "size": 238, "time": "2021-04-05 06:06:31", "crc": "B82FEC6E"}, {"name": "AGB-AY6J-JPN-0046.minigsf", "size": 240, "time": "2021-04-05 06:06:31", "crc": "42C3151E"}, {"name": "AGB-AY6J-JPN-0047.minigsf", "size": 238, "time": "2021-04-05 06:06:31", "crc": "783CF90B"}, {"name": "AGB-AY6J-JPN-0048.minigsf", "size": 239, "time": "2021-04-05 06:06:31", "crc": "50A14DEC"}, {"name": "AGB-AY6J-JPN-0049.minigsf", "size": 240, "time": "2021-04-05 06:06:31", "crc": "97C0B4BF"}, {"name": "AGB-AY6J-JPN-0050.minigsf", "size": 238, "time": "2021-04-05 06:06:31", "crc": "DB14345E"}, {"name": "AGB-AY6J-JPN.gsflib", "size": 145302, "time": "2019-01-12 08:31:59", "crc": "051002E9"}, {"name": "src/AGB-AY6J-JPN-GSF.ips", "size": 27, "time": "2019-01-12 08:12:49", "crc": "7D5F5B82"}]}