{"type": "7z", "size": 78888012, "method": "LZMA2:24", "solid": true, "files": [{"name": "bgm_3000.ogg", "size": 1022735, "time": "2021-04-03 22:59:35", "crc": "1B0FAB58"}, {"name": "bgm_50000.ogg", "size": 756358, "time": "2021-04-03 22:59:35", "crc": "3ED59B73"}, {"name": "chara_01_202002_01.ogg", "size": 3575699, "time": "2021-04-03 22:59:35", "crc": "D88F6F30"}, {"name": "chara_02_202003_01.ogg", "size": 2292543, "time": "2021-04-03 22:59:35", "crc": "C8117B75"}, {"name": "chara_03_202006_01.ogg", "size": 1641438, "time": "2021-04-03 22:59:35", "crc": "5D50520A"}, {"name": "chara_04_202010_01.ogg", "size": 2044225, "time": "2021-04-03 22:59:35", "crc": "D104F8C8"}, {"name": "chara_05_202012_01.ogg", "size": 1709418, "time": "2021-04-03 22:59:35", "crc": "B172A9DC"}, {"name": "life_will_change.ogg", "size": 4602059, "time": "2021-04-03 22:59:35", "crc": "D2F034AF"}, {"name": "me_quest_clear.ogg", "size": 831717, "time": "2021-04-03 22:59:35", "crc": "7B811C59"}, {"name": "me_quest_gameover.ogg", "size": 789463, "time": "2021-04-03 22:59:35", "crc": "1ED17113"}, {"name": "rays_battle.ogg", "size": 1336168, "time": "2021-04-03 22:59:35", "crc": "21E19A15"}, {"name": "rays_boss.ogg", "size": 1146638, "time": "2021-04-03 22:59:35", "crc": "60CBAB18"}, {"name": "sao5_01_qst_sao_01.ogg", "size": 2017885, "time": "2021-04-03 22:59:35", "crc": "1C33179C"}, {"name": "sao5_02_qst_alo_01.ogg", "size": 2214095, "time": "2021-04-03 22:59:35", "crc": "8E19C161"}, {"name": "sao5_03_qst_ggo_01.ogg", "size": 1737449, "time": "2021-04-03 22:59:35", "crc": "0E7A1EF6"}, {"name": "sao5_04_boss_sao_01.ogg", "size": 1536923, "time": "2021-04-03 22:59:35", "crc": "9666F6D9"}, {"name": "sao5_05_boss_alo_02.ogg", "size": 1378423, "time": "2021-04-03 22:59:35", "crc": "520C7C00"}, {"name": "sao5_06_boss_ggo_01.ogg", "size": 1600040, "time": "2021-04-03 22:59:35", "crc": "7C093239"}, {"name": "sao5_07_mt_04.ogg", "size": 1933298, "time": "2021-04-03 22:59:35", "crc": "109BC7BE"}, {"name": "sao5_08_town_03.ogg", "size": 1820990, "time": "2021-04-03 22:59:35", "crc": "D9D9EA14"}, {"name": "sao5_09_party_04.ogg", "size": 1022735, "time": "2021-04-03 22:59:35", "crc": "1B0FAB58"}, {"name": "sao5_10_gacha_01.ogg", "size": 1044066, "time": "2021-04-03 22:59:35", "crc": "3B958703"}, {"name": "sao5_11_kajiya_01.ogg", "size": 1111909, "time": "2021-04-03 22:59:35", "crc": "28B509DA"}, {"name": "sao5_12_ev_btl_03.ogg", "size": 993376, "time": "2021-04-03 22:59:35", "crc": "1B3ED1F3"}, {"name": "sao5_13_worldmap_02.ogg", "size": 1055588, "time": "2021-04-03 22:59:35", "crc": "339BDE10"}, {"name": "sao5_14_result_01.ogg", "size": 831717, "time": "2021-04-03 22:59:35", "crc": "7B811C59"}, {"name": "sao5_15_everyday_01.ogg", "size": 1076022, "time": "2021-04-03 22:59:35", "crc": "AF35C1E1"}, {"name": "sao5_16_love_02.ogg", "size": 926925, "time": "2021-04-03 22:59:35", "crc": "06A15B49"}, {"name": "sao5_17_peace_01.ogg", "size": 912965, "time": "2021-04-03 22:59:35", "crc": "1570A9C5"}, {"name": "sao5_18_sad_01.ogg", "size": 1125517, "time": "2021-04-03 22:59:35", "crc": "D1768AB7"}, {"name": "sao5_19_worry_02.ogg", "size": 1025071, "time": "2021-04-03 22:59:35", "crc": "232D096C"}, {"name": "sao5_20_strategy_01.ogg", "size": 1108323, "time": "2021-04-03 22:59:35", "crc": "0E973868"}, {"name": "sao5_21_front_boss_04.ogg", "size": 1134953, "time": "2021-04-03 22:59:35", "crc": "EA6DC3B4"}, {"name": "sao5_22_setsunai_01.ogg", "size": 789463, "time": "2021-04-03 22:59:35", "crc": "1ED17113"}, {"name": "sao5_23_smile_01.ogg", "size": 920383, "time": "2021-04-03 22:59:35", "crc": "BA9ABCBC"}, {"name": "sao5_24_comical_01.ogg", "size": 1093988, "time": "2021-04-03 22:59:35", "crc": "D70E83BB"}, {"name": "sao5_25_despair_01.ogg", "size": 1024414, "time": "2021-04-03 22:59:35", "crc": "49CCA5E5"}, {"name": "sao5_26_sao_forest_01.ogg", "size": 2159064, "time": "2021-04-03 22:59:35", "crc": "405F81CA"}, {"name": "sao5_27_sao_dg_03.ogg", "size": 1787818, "time": "2021-04-03 22:59:35", "crc": "170DB6C8"}, {"name": "sao5_28_sao_snow_01.ogg", "size": 4309712, "time": "2021-04-03 22:59:35", "crc": "4F9F3844"}, {"name": "sao5_29_alo_gqst_01.ogg", "size": 2038158, "time": "2021-04-03 22:59:35", "crc": "99C6FAB7"}, {"name": "sao5_30_sao_boss_h_01.ogg", "size": 1288801, "time": "2021-04-03 22:59:35", "crc": "1CD2D2BF"}, {"name": "sao5_31_alo_boss_yjn_01.ogg", "size": 1638991, "time": "2021-04-03 22:59:35", "crc": "47FCC53E"}, {"name": "sao5_32_sao_adv_btl_01.ogg", "size": 1119915, "time": "2021-04-03 22:59:35", "crc": "3ED34655"}, {"name": "sao5_33_sao_friend_01.ogg", "size": 985084, "time": "2021-04-03 22:59:35", "crc": "63BDAF29"}, {"name": "sao5_34_asuna_hospital_01.ogg", "size": 1019399, "time": "2021-04-03 22:59:35", "crc": "F027C003"}, {"name": "sao5_35_trauma_01.ogg", "size": 2157356, "time": "2021-04-03 22:59:35", "crc": "8F3981A2"}, {"name": "sao5_36_title_01.ogg", "size": 1933298, "time": "2021-04-03 22:59:35", "crc": "109BC7BE"}, {"name": "sao5_37_town_01.ogg", "size": 1820990, "time": "2021-04-03 22:59:35", "crc": "D9D9EA14"}, {"name": "sao5_38_helheim_battle_01.ogg", "size": 1058727, "time": "2021-04-03 22:59:35", "crc": "6423A947"}, {"name": "sao5_39_np_battle_01.ogg", "size": 1450527, "time": "2021-04-03 22:59:35", "crc": "A1D4BBD6"}, {"name": "sao5_40_np_boss_battle_01.ogg", "size": 1405747, "time": "2021-04-03 22:59:35", "crc": "31B392D2"}]}