{"type": "7z", "size": 219185891, "method": "LZMA:24", "solid": true, "files": [{"name": "PAC_00000001.ss2", "size": 27842600, "crc": "B3AFCBD4"}, {"name": "PAC_00004EB3.genh", "size": 7573504, "crc": "8D9254F9"}, {"name": "PAC_00004EB4.genh", "size": 8294400, "crc": "52BF7E1F"}, {"name": "PAC_00004EB5.genh", "size": 10391552, "crc": "97652E54"}, {"name": "PAC_00004EB6.genh", "size": 8851456, "crc": "0A760C8B"}, {"name": "PAC_00004EB7.genh", "size": 8032256, "crc": "C9AB8AA2"}, {"name": "PAC_00004EB8.genh", "size": 12324864, "crc": "1351864E"}, {"name": "PAC_00004EB9.genh", "size": 5148672, "crc": "BFF40C6C"}, {"name": "PAC_00004EBA.genh", "size": 8654848, "crc": "51DB8FFE"}, {"name": "PAC_00004EBB.genh", "size": 7639040, "crc": "8FE76C00"}, {"name": "PAC_00004EBC.genh", "size": 6885376, "crc": "F251A0F7"}, {"name": "PAC_00004EBD.genh", "size": 7606272, "crc": "0C166B64"}, {"name": "PAC_00004EBE.genh", "size": 430080, "crc": "658712D4"}, {"name": "PAC_00004EBF.genh", "size": 9670656, "crc": "83B832E1"}, {"name": "PAC_00004EC0.genh", "size": 9932800, "crc": "7D65337C"}, {"name": "PAC_00004EC1.genh", "size": 10293248, "crc": "5C48FC23"}, {"name": "PAC_00004EC2.genh", "size": 8130560, "crc": "5A957136"}, {"name": "PAC_00004EC3.genh", "size": 7278592, "crc": "48DB07CA"}, {"name": "PAC_00004EC4.genh", "size": 7278592, "crc": "E07A66D0"}, {"name": "PAC_00004EC5.genh", "size": 9900032, "crc": "8DF0FD9D"}, {"name": "PAC_00004EC6.genh", "size": 6328320, "crc": "56C13F3C"}, {"name": "PAC_00004EC7.genh", "size": 7540736, "crc": "7C737BA3"}, {"name": "PAC_00004EC8.genh", "size": 5115904, "crc": "6223EEF0"}, {"name": "PAC_00004EC9.genh", "size": 7081984, "crc": "D5D681BA"}, {"name": "PAC_00004ECA.genh", "size": 7409664, "crc": "C4B50D18"}, {"name": "PAC_00004ECB.genh", "size": 5443584, "crc": "43E54946"}, {"name": "PAC_00004ECC.genh", "size": 6131712, "crc": "14B663B5"}, {"name": "PAC_00004ECD.genh", "size": 9342976, "crc": "C645304A"}, {"name": "PAC_00004ECE.genh", "size": 7311360, "crc": "4F6242AA"}, {"name": "PAC_00004ECF.genh", "size": 7213056, "crc": "F214A359"}, {"name": "PAC_00004ED0.genh", "size": 7409664, "crc": "3BA1EFEE"}, {"name": "PAC_00004ED1.genh", "size": 8032256, "crc": "8A227BAC"}, {"name": "PAC_00004ED2.genh", "size": 7933952, "crc": "AA916F84"}, {"name": "PAC_00004ED3.genh", "size": 7409664, "crc": "B042B6FF"}]}