{"type": "zip", "size": 85572, "files": [{"name": "IBGM.EXE", "size": 17096, "time": "1996-12-24 23:32:00", "crc": "FF2CE567"}, {"name": "IBGMP.COM", "size": 90, "time": "1996-12-24 23:32:00", "crc": "D4FB525C"}, {"name": "IBGMPM.COM", "size": 117, "time": "1996-12-24 23:32:00", "crc": "09B19C40"}, {"name": "RYOF0001.MID", "size": 27197, "time": "1996-12-24 23:32:00", "crc": "853B02B8"}, {"name": "RYOF0002.MID", "size": 18264, "time": "1996-12-24 23:32:00", "crc": "5A9584BB"}, {"name": "RYOF0003.MID", "size": 265, "time": "1996-12-24 23:32:00", "crc": "4FB78D87"}, {"name": "RYOF0004.MID", "size": 5000, "time": "1996-12-24 23:32:00", "crc": "FC0EB675"}, {"name": "RYOF0005.MID", "size": 25635, "time": "1996-12-24 23:32:00", "crc": "E931B1A0"}, {"name": "RYOF0006.MID", "size": 8160, "time": "1996-12-24 23:32:00", "crc": "9D077738"}, {"name": "RYOF0007.MID", "size": 11954, "time": "1996-12-24 23:32:00", "crc": "2E232EDB"}, {"name": "RYOF0008.MID", "size": 17319, "time": "1996-12-24 23:32:00", "crc": "C2A04554"}, {"name": "RYOF0009.MID", "size": 8493, "time": "1996-12-24 23:32:00", "crc": "F73E8E26"}, {"name": "RYOF0010.MID", "size": 25067, "time": "1996-12-24 23:32:00", "crc": "C61ECD76"}, {"name": "RYOM0001.MID", "size": 26514, "time": "1996-12-24 23:32:00", "crc": "EB8BF56F"}, {"name": "RYOM0002.MID", "size": 19731, "time": "1996-12-24 23:32:00", "crc": "0EEDF775"}, {"name": "RYOM0003.MID", "size": 265, "time": "1996-12-24 23:32:00", "crc": "B62E1A8E"}, {"name": "RYOM0004.MID", "size": 4999, "time": "1996-12-24 23:32:00", "crc": "1D349B52"}, {"name": "RYOM0005.MID", "size": 30468, "time": "1996-12-24 23:32:00", "crc": "45FCA2C1"}, {"name": "RYOM0006.MID", "size": 6612, "time": "1996-12-24 23:32:00", "crc": "8DCF76A4"}, {"name": "RYOM0007.MID", "size": 13242, "time": "1996-12-24 23:32:00", "crc": "7198C570"}, {"name": "RYOM0008.MID", "size": 17278, "time": "1996-12-24 23:32:00", "crc": "4F0EAAAE"}, {"name": "RYOM0009.MID", "size": 8417, "time": "1996-12-24 23:32:00", "crc": "929DF072"}, {"name": "RYOM0010.MID", "size": 26710, "time": "1996-12-24 23:32:00", "crc": "1962F316"}]}