{"type": "zip", "size": 21133, "files": [{"name": "NAX.COM", "size": 18493, "time": "1996-12-24 23:32:00", "crc": "F3F9FD02"}, {"name": "NLP_HOOT.COM", "size": 384, "time": "1996-12-24 23:32:00", "crc": "B8EA2D05"}, {"name": "WF1.O", "size": 6919, "time": "1996-12-24 23:32:00", "crc": "5803C714"}, {"name": "WF2.O", "size": 4456, "time": "1996-12-24 23:32:00", "crc": "7945C9C9"}, {"name": "WF3.O", "size": 6648, "time": "1996-12-24 23:32:00", "crc": "1D4493D2"}, {"name": "WF4.O", "size": 4412, "time": "1996-12-24 23:32:00", "crc": "A96E1FD8"}, {"name": "WF5.O", "size": 5880, "time": "1996-12-24 23:32:00", "crc": "08B18DD9"}, {"name": "WF6.O", "size": 1423, "time": "1996-12-24 23:32:00", "crc": "F526A5B5"}, {"name": "WF7.O", "size": 2878, "time": "1996-12-24 23:32:00", "crc": "7D54E765"}]}