{"type": "7z", "size": 24884195, "method": "LZMA:24", "solid": true, "files": [{"name": "CorpseSting01.mp3", "size": 336276, "crc": "31FC21AF"}, {"name": "EUTSTheme01.mp3", "size": 3919200, "crc": "A0AFFFA5"}, {"name": "EUTSTheme01Sting.mp3", "size": 774624, "crc": "E8F4EA9A"}, {"name": "EUTSTheme02.mp3", "size": 3677856, "crc": "EAE9E18D"}, {"name": "EUTSTheme02Sting.mp3", "size": 566496, "crc": "960DA7B2"}, {"name": "HastingsTheme01.mp3", "size": 1330990, "crc": "7D3E11C3"}, {"name": "LeathercombeBay01.mp3", "size": 2511109, "crc": "DE8B45F0"}, {"name": "Mood_2.wav", "size": 3790644, "crc": "A8BFAC9A"}, {"name": "PoirotEvilSting01.mp3", "size": 363205, "crc": "26021E8A"}, {"name": "PoirotsTheme01.mp3", "size": 1569120, "crc": "F30D5665"}, {"name": "PoirotsThemeSting.mp3", "size": 483109, "crc": "47CA897A"}, {"name": "SomethingsupSting.mp3", "size": 342770, "crc": "FDB305B1"}, {"name": "TheChase.mp3", "size": 1599777, "crc": "D9A6E23C"}, {"name": "TheGatheringStorm.mp3", "size": 1971744, "crc": "30893F7F"}, {"name": "TheGhost01.mp3", "size": 2633142, "crc": "38AF955E"}, {"name": "TitleThemeStingV2.mp3", "size": 375264, "crc": "024E64FA"}]}